[
  {
    "gameId": "750381",
    "date": "Sunday, December 28, 2025",
    "team1": "Arouca",
    "score": "2 - 2",
    "team2": "Gil Vicente",
    "title": "Arouca VS Gil Vicente",
    "match_url": "https://www.espn.com/soccer/match/_/gameId/750381/gil-vicente-arouca"
  },
  {
    "gameId": "750383",
    "date": "Sunday, December 28, 2025",
    "team1": "Casa Pia",
    "score": "0 - 0",
    "team2": "Vit贸ria de Guimaraes",
    "title": "Casa Pia VS Vit贸ria de Guimaraes",
    "match_url": "https://www.espn.com/soccer/match/_/gameId/750383/vitoria-de-guimaraes-casa-pia"
  },
  {
    "gameId": "750386",
    "date": "Sunday, December 28, 2025",
    "team1": "Braga",
    "score": "2 - 2",
    "team2": "Benfica",
    "title": "Braga VS Benfica",
    "match_url": "https://www.espn.com/soccer/match/_/gameId/750386/benfica-braga"
  },
  {
    "gameId": "750385",
    "date": "Sunday, December 28, 2025",
    "team1": "Sporting CP",
    "score": "4 - 0",
    "team2": "Rio Ave",
    "title": "Sporting CP VS Rio Ave",
    "match_url": "https://www.espn.com/soccer/match/_/gameId/750385/rio-ave-sporting-cp"
  },
  {
    "gameId": "750389",
    "date": "Monday, December 29, 2025",
    "team1": "FC Porto",
    "score": "2 - 0",
    "team2": "AVS",
    "title": "FC Porto VS AVS",
    "match_url": "https://www.espn.com/soccer/match/_/gameId/750389/avs-fc-porto"
  },
  {
    "gameId": "750393",
    "date": "Friday, January 2, 2026",
    "team1": "Gil Vicente",
    "score": "1 - 1",
    "team2": "Sporting CP",
    "title": "Gil Vicente VS Sporting CP",
    "match_url": "https://www.espn.com/soccer/match/_/gameId/750393/sporting-cp-gil-vicente"
  },
  {
    "gameId": "750390",
    "date": "Friday, January 2, 2026",
    "team1": "Vit贸ria de Guimaraes",
    "score": "2 - 1",
    "team2": "C.D. Nacional",
    "title": "Vit贸ria de Guimaraes VS C.D. Nacional",
    "match_url": "https://www.espn.com/soccer/match/_/gameId/750390/cd-nacional-vitoria-de-guimaraes"
  }
]